pydocgen/__main__.py
pydocgen/documentation_generator.py
pydocgen/helper.py
pydocgen-0.0.4rc0.dist-info/LICENSE
pydocgen-0.0.4rc0.dist-info/METADATA
pydocgen-0.0.4rc0.dist-info/WHEEL
pydocgen-0.0.4rc0.dist-info/entry_points.txt
pydocgen-0.0.4rc0.dist-info/top_level.txt
pydocgen-0.0.4rc0.dist-info/RECORD
