Metadata-Version: 2.1
Name: pydocgen
Version: 0.0.4rc0
Summary: Automatically generate docstrings and documentation files for your code!
Home-page: https://github.com/m0bi5/pydocgen
Author: m0bi5
Author-email: 
License: MIT
Platform: UNKNOWN
Classifier: Topic :: Documentation
Classifier: Topic :: Software Development :: Documentation
Classifier: Topic :: Utilities
Classifier: License :: OSI Approved :: MIT License
Classifier: Programming Language :: Python :: 3 :: Only
Requires-Dist: pdoc3
Requires-Dist: Jinja2
